{
  "users": [
    {
      "id": "3",
      "email": "codyvandijk@realestatecare.com",
      "password": "admin123"
    },
    {
      "id": "4",
      "email": "jennasmith@realestatecare.com",
      "password": "admin101"
    },
    {
      "id": "5",
      "email": "emilybosch@realestatecare.com",
      "password": "admin456"
    }
  ],
  "inspections": [
    {
      "id": "1",
      "type": "InProgress",
      "status": "In progress",
      "details": "Open inspection scheduled for location A.",
      "address": "123 Maple St, Springfield",
      "scheduledDate": "2023-12-01"
    },
    {
      "id": "2",
      "type": "Completed",
      "status": "Closed",
      "details": "Completed inspection at location B.",
      "address": "456 Oak St, Metropolis",
      "completedDate": "2023-11-25"
    },
    {
      "id": "3",
      "type": "Open",
      "status": "In progress",
      "details": "Open inspection scheduled for location C.",
      "address": "789 Pine St, Gotham",
      "scheduledDate": "2023-12-03"
    },
    {
      "id": "4",
      "type": "Completed",
      "status": "Closed",
      "details": "Completed inspection at location D.",
      "address": "101 Elm St, Star City",
      "completedDate": "2023-11-15"
    },
    {
      "id": "5",
      "type": "InProgress",
      "status": "In progress",
      "details": "Inspection currently underway at location E.",
      "address": "202 Birch St, Central City",
      "scheduledDate": "2023-12-02"
    }
  ],
  "knowledgeBase": [
    {
      "id": "1",
      "title": "Inspection Guidelines",
      "description": "Comprehensive guidelines for property inspections.",
      "fileUrl": "https://example.com/inspection-guidelines.pdf"
    },
    {
      "id": "2",
      "title": "Maintenance Checklist",
      "description": "Checklist for deferred maintenance tasks.",
      "fileUrl": "https://example.com/maintenance-checklist.pdf"
    },
    {
      "id": "3",
      "title": "Fire Safety Procedures",
      "description": "Standard operating procedures for fire hazard assessments.",
      "fileUrl": "https://example.com/fire-safety-procedures.pdf"
    }
  ],
  "settings": {
    "userPreferences": {
      "theme": "light", 
      "notifications": true
    },
    "accountDetails": {
      "name": "John Doe",
      "email": "johndoe@realestatecare.com",
      "avatar": "https://example.com/avatar.jpg"
    }
  }
}
